a5/__init__.py
a5/core/__init__.py
a5/core/cell.py
a5/core/cell_info.py
a5/core/compact.py
a5/core/constants.py
a5/core/coordinate_systems.py
a5/core/coordinate_transforms.py
a5/core/dodecahedron_quaternions.py
a5/core/hex.py
a5/core/hilbert.py
a5/core/origin.py
a5/core/pentagon.py
a5/core/serialization.py
a5/core/tiling.py
a5/core/utils.py
a5/core/warp.py
a5/geometry/__init__.py
a5/geometry/pentagon.py
a5/geometry/spherical_polygon.py
a5/geometry/spherical_triangle.py
a5/math/__init__.py
a5/math/quat.py
a5/math/vec2.py
a5/math/vec3.py
a5/projections/authalic.py
a5/projections/crs.py
a5/projections/dodecahedron.py
a5/projections/gnomonic.py
a5/projections/polyhedral.py
pya5-0.6.1.dist-info/METADATA
pya5-0.6.1.dist-info/WHEEL
pya5-0.6.1.dist-info/licenses/LICENSE
pya5-0.6.1.dist-info/RECORD
