Metadata-Version: 2.4
Name: pya5
Version: 0.6.1
Summary: A5 - Global Pentagonal Geospatial Index
License:                                  Apache License
License-File: LICENSE
Requires-Python: >=3.8
Provides-Extra: test
Requires-Dist: pytest>=7.0.0; extra == 'test'
